dev/__init__.py
dev/config/__init__.py
dev/config/create_yaml.py
dev/database/__init__.py
dev/database/load_sample_data.py
doc/source/conf.py
pyramid_oereb/__init__.py
pyramid_oereb/contrib/__init__.py
pyramid_oereb/contrib/data_sources/__init__.py
pyramid_oereb/contrib/data_sources/create_tables.py
pyramid_oereb/contrib/data_sources/interlis_2_3/__init__.py
pyramid_oereb/contrib/data_sources/interlis_2_3/hook_methods.py
pyramid_oereb/contrib/data_sources/interlis_2_3/interlis_2_3_utils.py
pyramid_oereb/contrib/data_sources/interlis_2_3/models/__init__.py
pyramid_oereb/contrib/data_sources/interlis_2_3/models/theme.py
pyramid_oereb/contrib/data_sources/interlis_2_3/sources/__init__.py
pyramid_oereb/contrib/data_sources/interlis_2_3/sources/plr.py
pyramid_oereb/contrib/data_sources/oereblex/__init__.py
pyramid_oereb/contrib/data_sources/oereblex/create_tables.py
pyramid_oereb/contrib/data_sources/oereblex/models/__init__.py
pyramid_oereb/contrib/data_sources/oereblex/models/theme.py
pyramid_oereb/contrib/data_sources/oereblex/sources/__init__.py
pyramid_oereb/contrib/data_sources/oereblex/sources/document.py
pyramid_oereb/contrib/data_sources/oereblex/sources/plr_oereblex.py
pyramid_oereb/contrib/data_sources/standard/__init__.py
pyramid_oereb/contrib/data_sources/standard/create_tables.py
pyramid_oereb/contrib/data_sources/standard/hook_methods.py
pyramid_oereb/contrib/data_sources/standard/models/__init__.py
pyramid_oereb/contrib/data_sources/standard/models/main.py
pyramid_oereb/contrib/data_sources/standard/models/theme.py
pyramid_oereb/contrib/data_sources/standard/sources/__init__.py
pyramid_oereb/contrib/data_sources/standard/sources/address.py
pyramid_oereb/contrib/data_sources/standard/sources/availability.py
pyramid_oereb/contrib/data_sources/standard/sources/data_integration.py
pyramid_oereb/contrib/data_sources/standard/sources/disclaimer.py
pyramid_oereb/contrib/data_sources/standard/sources/document.py
pyramid_oereb-2.5.8.dist-info/licenses/LICENSE.txt
pyramid_oereb-2.5.8.dist-info/METADATA
pyramid_oereb-2.5.8.dist-info/WHEEL
pyramid_oereb-2.5.8.dist-info/entry_points.txt
pyramid_oereb-2.5.8.dist-info/top_level.txt
pyramid_oereb-2.5.8.dist-info/RECORD
