Metadata-Version: 2.4
Name: pyramid_oereb
Version: 2.5.8
Summary: pyramid_oereb, extension for pyramid web frame work to provide a basic server part for the oereb project
Author-email: François Voisard <francois.voisard@ne.ch>
License: BSD 2-Clause License
Project-URL: Repository, https://github.com/openoereb/pyramid_oereb
Project-URL: Changelog, https://github.com/openoereb/pyramid_oereb/blob/master/CHANGES.rst
Keywords: pyramid oereb
Classifier: Development Status :: 5 - Production/Stable
Classifier: Intended Audience :: Developers
Classifier: Programming Language :: Python :: 3.10
Classifier: Programming Language :: Python :: 3.11
Classifier: Programming Language :: Python :: 3.12
Classifier: Programming Language :: Python :: 3.13
Classifier: Programming Language :: Python :: 3.14
Classifier: Framework :: Pyramid
Classifier: Topic :: Internet :: WWW/HTTP
Classifier: Topic :: Internet :: WWW/HTTP :: WSGI :: Application
License-File: LICENSE.txt
Provides-Extra: recommend
Requires-Dist: pypdf==5.9.0; extra == "recommend"
Requires-Dist: filetype==1.2.0; extra == "recommend"
Requires-Dist: geoalchemy2==0.17.1; extra == "recommend"
Requires-Dist: pyramid==2.0.2; extra == "recommend"
Requires-Dist: pyramid-debugtoolbar==4.12.1; extra == "recommend"
Requires-Dist: qrcode==8.2; extra == "recommend"
Requires-Dist: image==1.5.33; extra == "recommend"
Requires-Dist: shapely==2.1.2; extra == "recommend"
Requires-Dist: SQLAlchemy==2.0.44; extra == "recommend"
Requires-Dist: pyaml-env==1.2.2; extra == "recommend"
Requires-Dist: urllib3==2.5.0; extra == "recommend"
Requires-Dist: waitress==3.0.2; extra == "recommend"
Requires-Dist: pyreproj==3.0.0; extra == "recommend"
Requires-Dist: mako-render==0.1.0; extra == "recommend"
Requires-Dist: requests==2.32.5; extra == "recommend"
Requires-Dist: geolink-formatter==2.0.7; extra == "recommend"
Requires-Dist: c2cwsgiutils[standard]==6.1.8; extra == "recommend"
Provides-Extra: no-version
Requires-Dist: pypdf; extra == "no-version"
Requires-Dist: filetype; extra == "no-version"
Requires-Dist: geoalchemy2; extra == "no-version"
Requires-Dist: pyramid; extra == "no-version"
Requires-Dist: pyramid-debugtoolbar; extra == "no-version"
Requires-Dist: qrcode; extra == "no-version"
Requires-Dist: image; extra == "no-version"
Requires-Dist: shapely; extra == "no-version"
Requires-Dist: SQLAlchemy; extra == "no-version"
Requires-Dist: pyaml-env; extra == "no-version"
Requires-Dist: urllib3; extra == "no-version"
Requires-Dist: waitress; extra == "no-version"
Requires-Dist: pyreproj; extra == "no-version"
Requires-Dist: mako-render; extra == "no-version"
Requires-Dist: requests; extra == "no-version"
Requires-Dist: geolink-formatter; extra == "no-version"
Requires-Dist: c2cwsgiutils[standard]; extra == "no-version"
Provides-Extra: testing
Requires-Dist: jsonschema==4.25.1; extra == "testing"
Requires-Dist: lxml==5.4.0; extra == "testing"
Requires-Dist: pytest==8.4.2; extra == "testing"
Requires-Dist: pytest-cov==6.3.0; extra == "testing"
Requires-Dist: pytest-ordering==0.6; extra == "testing"
Requires-Dist: requests-mock==1.12.1; extra == "testing"
Requires-Dist: responses==0.25.8; extra == "testing"
Requires-Dist: webtest==3.0.7; extra == "testing"
Requires-Dist: pillow==12; extra == "testing"
Provides-Extra: dev
Requires-Dist: flake8==7.3.0; extra == "dev"
Requires-Dist: Flake8-pyproject==1.2.3; extra == "dev"
Requires-Dist: pyflakes==3.4.0; extra == "dev"
Requires-Dist: pycodestyle==2.14.0; extra == "dev"
Requires-Dist: Sphinx==7.4.7; extra == "dev"
Requires-Dist: sphinx_rtd_theme==3.0.2; extra == "dev"
Requires-Dist: psycopg2==2.9.11; extra == "dev"
Requires-Dist: mccabe==0.7.0; extra == "dev"
Requires-Dist: c2c.template==2.4.2; extra == "dev"
Requires-Dist: yappi; extra == "dev"
Dynamic: license-file
